jacknote_s3
