Metadata-Version: 2.1
Name: jacknote-s3
Version: 0.1.3
Summary: Jacknote
Home-page: https://radioframenetworks.com.com/kacknote
Author: jdev
Author-email: jdev@radioframenetworks.com
License: UNKNOWN
Platform: UNKNOWN
